swarmauri_tool_jupytergetshellmessage/JupyterGetShellMessageTool.py
swarmauri_tool_jupytergetshellmessage/__init__.py
swarmauri_tool_jupytergetshellmessage/install_kernel.py
swarmauri_tool_jupytergetshellmessage-0.7.5.dist-info/LICENSE
swarmauri_tool_jupytergetshellmessage-0.7.5.dist-info/METADATA
swarmauri_tool_jupytergetshellmessage-0.7.5.dist-info/WHEEL
swarmauri_tool_jupytergetshellmessage-0.7.5.dist-info/entry_points.txt
swarmauri_tool_jupytergetshellmessage-0.7.5.dist-info/RECORD
