Metadata-Version: 2.3
Name: swarmauri_tool_jupytergetshellmessage
Version: 0.7.5
Summary: A tool designed to retrieve shell messages from a running Jupyter kernel using jupyter_client, useful for debugging execution responses.
License: Apache-2.0
Author: Jacob Stewart
Author-email: jacob@swarmauri.com
Requires-Python: >=3.10,<3.13
Classifier: License :: OSI Approved :: Apache Software License
Classifier: Programming Language :: Python :: 3.10
Classifier: Programming Language :: Python :: 3.11
Classifier: Programming Language :: Python :: 3.12
Classifier: Programming Language :: Python :: 3.13
Requires-Dist: ipykernel (>=6.29.5)
Requires-Dist: jupyter_client (>=8.6.3)
Requires-Dist: swarmauri_base
Requires-Dist: swarmauri_core
Requires-Dist: swarmauri_standard
